{
  "airlines": [
    {
      "name": "Vietnam Airlines",
      "code": "VN",
      "logo": "images/vn_logo.png",
      "luggage": "10kg xách tay và 1 kiện 23kg hành lý ký gửi",
      "meal": true
    },
    {
      "name": "Vietjet Air",
      "code": "VJ",
      "logo": "images/vj_logo.png",
      "luggage": "7kg xách tay và 1 kiện 20kg hành lý ký gửi",
      "meal": false
    },
    {
      "name": "Bamboo Airways",
      "code": "QH",
      "logo": "images/qh_logo.png",
      "luggage": "7kg xách tay và 1 kiện 20kg hành lý ký gửi",
      "meal": false
    },
    {
      "name": "Pacific Airlines",
      "code": "BL",
      "logo": "images/bl_logo.png",
      "luggage": "7kg xách tay và 1 kiện 23kg hành lý ký gửi",
      "meal": false
    },
    {
      "name": "Vietravel Airlines",
      "code": "VU",
      "logo": "images/vu_logo.png",
      "luggage": "7kg xách tay và 1 kiện 15kg hành lý ký gửi",
      "meal": false
    },
    {
      "name": "Singapore Airlines",
      "code": "SQ",
      "logo": "images/sq_logo.png",
      "luggage": "7kg xách tay và 25kg ký gửi",
      "meal": true
    },
    {
      "name": "Thai Airways",
      "code": "TG",
      "logo": "images/tg_logo.png",
      "luggage": "7kg xách tay và 1 kiện 30kg hành lý ký gửi",
      "meal": true
    },
    {
      "name": "Japan Airlines",
      "code": "JL",
      "logo": "images/jl_logo.png",
      "luggage": "7kg xách tay và 1 kiện 23kg hành lý ký gửi",
      "meal": true
    },
    {
      "name": "Cathay Pacific",
      "code": "CX",
      "logo": "images/cx_logo.png",
      "luggage": "7kg xách tay và 1 kiện 23kg hành lý ký gửi",
      "meal": true
    },
    {
      "name": "Emirates",
      "code": "EK",
      "logo": "images/ek_logo.png",
      "luggage": "7kg xách tay và 30kg ký gửi",
      "meal": true
    },
    {
      "name": "Qatar Airways",
      "code": "QR",
      "logo": "images/qr_logo.png",
      "luggage": "7kg xách tay và 30kg ký gửi",
      "meal": true
    },
    {
      "name": "Korean Air",
      "code": "KE",
      "logo": "images/ke_logo.png",
      "luggage": "7kg xách tay và 1 kiện 23kg hành lý ký gửi",
      "meal": true
    },
    {
      "name": "All Nippon Airways",
      "code": "NH",
      "logo": "images/nh_logo.png",
      "luggage": "7kg xách tay và 1 kiện 23kg hành lý ký gửi",
      "meal": true
    },
    {
      "name": "Lufthansa",
      "code": "LH",
      "logo": "images/lh_logo.png",
      "luggage": "7kg xách tay và 1 kiện 23kg hành lý ký gửi",
      "meal": true
    },
    {
      "name": "Air France",
      "code": "AF",
      "logo": "images/af_logo.png",
      "luggage": "7kg xách tay và 1 kiện 23kg hành lý ký gửi",
      "meal": true
    },
    {
      "name": "Qantas",
      "code": "QF",
      "logo": "images/qf_logo.png",
      "luggage": "7kg xách tay và 1 kiện 23kg hành lý ký gửi",
      "meal": true
    },
	{
	  "name": "China Southern Airlines",
	  "code": "CZ",
	  "logo": "images/cz_logo.png",
	  "luggage": "7kg xách tay và 1 kiện 23kg hành lý ký gửi",
	  "meal": false
	},
	{
	  "name": "Cambodia Angkor Air",
	  "code": "K6",
	  "logo": "images/k6_logo.png",
	  "luggage": "7kg xách tay và 1 kiện 20kg hành lý ký gửi",
	  "meal": false
	},
	{
	  "name": "Lao Airlines",
	  "code": "QV",
	  "logo": "images/qv_logo.png",
	  "luggage": "7kg xách tay và 1 kiện 20kg hành lý ký gửi",
	  "meal": true
	},
	{
	  "name": "Bangkok Airways",
	  "code": "PG",
	  "logo": "images/pg_logo.png",
	  "luggage": "7kg xách tay và 1 kiện 23kg hành lý ký gửi",
	  "meal": false
	},
	{
	  "name": "Garuda Indonesia",
	  "code": "GA",
	  "logo": "images/ga_logo.png",
	  "luggage": "7kg xách tay và 30kg hành lý ký gửi",
	  "meal": false
	},
	{
	  "name": "Malaysia Airlines",
	  "code": "MH",
	  "logo": "images/mh_logo.png",
	  "luggage": "7kg xách tay và 20kg hành lý ký gửi",
	  "meal": false
	},
	{
	  "name": "Philippine Airlines",
	  "code": "PR",
	  "logo": "images/pr_logo.png",
	  "luggage": "7kg xách tay và 1 kiện 30kg hành lý ký gửi",
	  "meal": false
	},
	{
	  "name": "Myanmar Airways International",
	  "code": "8M",
	  "logo": "images/8m_logo.png",
	  "luggage": "7kg xách tay và 30kg ký gửi",
	  "meal": false
	},
	{
	  "name": "Air China",
	  "code": "CA",
	  "logo": "images/ca_logo.png",
	  "luggage": "5kg xách tay và 2 kiện 23kg hành lý ký gửi",
	  "meal": false
	},
	{
	  "name": "Sichuan Airlines",
	  "code": "3U",
	  "logo": "images/3u_logo.png",
	  "luggage": "7kg xách tay và 1 kiện 23kg hành lý ký gửi",
	  "meal": false
	},
	{
	  "name": "Xiamen Airlines",
	  "code": "MF",
	  "logo": "images/mf_logo.png",
	  "luggage": "5kg xách tay và 2 kiện 23kg hành lý ký gửi",
	  "meal": false
	},
	{
	  "name": "China Airlines",
	  "code": "CI",
	  "logo": "images/ci_logo.png",
	  "luggage": "7kg xách tay và 2 kiện 23kg hành lý ký gửi",
	  "meal": false
	},
	{
	  "name": "Jeju Air",
	  "code": "7C",
	  "logo": "images/7c_logo.png",
	  "luggage": "7kg xách tay và 1 kiện 15kg hành lý ký gửi",
	  "meal": false
	},
	{
	  "name": "Asiana Airlines",
	  "code": "OZ",
	  "logo": "images/oz_logo.png",
	  "luggage": "7kg xách tay và 1 kiện 23kg hành lý ký gửi",
	  "meal": false
	},
	{
	  "name": "Korean Air",
	  "code": "KE",
	  "logo": "images/ke_logo.png",
	  "luggage": "7kg xách tay và 1 kiện 23kg hành lý ký gửi",
	  "meal": false
	},
	{
	  "name": "China Eastern Airlines",
	  "code": "MU",
	  "logo": "images/mu_logo.png",
	  "luggage": "7kg xách tay và 1 kiện 23kg hành lý ký gửi",
	  "meal": false
	},
	{
	  "name": "EVA Air",
	  "code": "BR",
	  "logo": "images/br_logo.png",
	  "luggage": "7kg xách tay và 1 kiện 23kg hành lý ký gửi",
	  "meal": true
	},
	{
	  "name": "Jett8 Airlines",
	  "code": "JX",
	  "logo": "images/j8_logo.png",
	  "luggage": "7kg xách tay và 2 kiện 23kg hành lý ký gửi",
	  "meal": true
	},
	{
	  "name": "Air India",
	  "code": "AI",
	  "logo": "images/ai_logo.png",
	  "luggage": "7kg xách tay và 1 kiện 25kg hành lý ký gửi",
	  "meal": true
	},
	{
	  "name": "Shenzhen Airlines",
	  "code": "ZH",
	  "logo": "images/zh_logo.png",
	  "luggage": "7kg xách tay và 1 kiện 23kg hành lý ký gửi",
	  "meal": true
	},
	{
	  "name": "Scoot",
	  "code": "TR",
	  "logo": "images/tr_logo.png",
	  "luggage": "7kg xách tay và 1 kiện 30kg hành lý ký gửi",
	  "meal": false
	}
  ],
  "child_price_ratio": 0.7
}